Computer architecture/LAB-4/ha.v
module halfadder(a,b,sum,carry);

input a,b;
output sum,carry;

and(sum,a,b);
xor(carry,a,b);

endmodule

Computer architecture/LAB-4/fa_using_ha.v
module fa_using_ha(a,b,c,sum,carry);

input a,b,c;
output sum;
output carry;

wire d;
wire e;
wire g;

halfadder adder1(a,b,d,e);
halfadder adder2(c,d,sum,g);
or(carry,g,e);

endmodule

Computer architecture/LAB-4/fa_ha_tb.v
module fa_ha_tb();

reg a;
reg b;
reg c;

wire sum;
wire carry;

fa_using_ha verify(a,b,c,sum,carry);

initial
begin
     $monitor("a=%b, b=%b, c=%b, sum=%b, carry=%b", a, b, c, sum, carry);
     $dumpfile("fa_using_ha.vcd");
     $dumpvars(0,fa_ha_tb);
     a = 0;b = 0;c = 0;#10;
     a = 0;b = 0;c = 1;#10;
     a = 0;b = 1;c = 0;#10;
     a = 0;b = 1;c = 1;#10;
     a = 1;b = 0;c = 0;#10;
     a = 1;b = 0;c = 1;#10;
     a = 1;b = 1;c = 0;#10;
     a = 1;b = 1;c = 1;#10;
end
endmodule

Computer architecture/LAB-4/fa_using_ha.vcd
$date
	Thu Feb 25 16:02:11 2021
$end
$version
	Icarus Verilog
$end
$timescale
	1s
$end
$scope module fa_ha_tb $end
$var wire 1 ! sum $end
$var wire 1 " carry $end
$var reg 1 # a $end
$var reg 1 $ b $end
$var reg 1 % c $end
$scope module verify $end
$var wire 1 # a $end
$var wire 1 $ b $end
$var wire 1 % c $end
$var wire 1 " carry $end
$var wire 1 ! sum $end
$var wire 1 & g $end
$var wire 1 ' e $end
$var wire 1 ( d $end
$scope module adder1 $end
$var wire 1 # a $end
$var wire 1 $ b $end
$var wire 1 ' carry $end
$var wire 1 ( sum $end
$upscope $end
$scope module adder2 $end
$var wire 1 % a $end
$var wire 1 ( b $end
$var wire 1 & carry $end
$var wire 1 ! sum $end
$upscope $end
$upscope $end
$upscope $end
$enddefinitions $end
#0
$dumpvars
0(
0'
0&
0%
0$
0#
0"
0!
$end
#10
1"
1&
1%
#20
0&
1'
0%
1$
#30
1&
1%
#40
0&
0%
0$
1#
#50
1&
1%
#60
1(
0'
0%
1$
#70
0"
1!
0&
1%
